glue_ar/__init__.py
glue_ar/ar.png
glue_ar/ar.svg
glue_ar/compression_draco.py
glue_ar/conftest.py
glue_ar/gltf_utils.py
glue_ar/logo.png
glue_ar/py.typed
glue_ar/registries.py
glue_ar/usd_utils.py
glue_ar/utils.py
glue_ar/common/__init__.py
glue_ar/common/export.py
glue_ar/common/export_dialog_base.py
glue_ar/common/export_options.py
glue_ar/common/export_state.py
glue_ar/common/gltf_animation.py
glue_ar/common/gltf_builder.py
glue_ar/common/marching_cubes.py
glue_ar/common/qr.py
glue_ar/common/ranged_callback.py
glue_ar/common/scatter.py
glue_ar/common/scatter_export_options.py
glue_ar/common/scatter_gltf.py
glue_ar/common/scatter_stl.py
glue_ar/common/scatter_usd.py
glue_ar/common/shapes.py
glue_ar/common/stl_builder.py
glue_ar/common/usd_builder.py
glue_ar/common/volume_export_options.py
glue_ar/common/voxels.py
glue_ar/common/tests/__init__.py
glue_ar/common/tests/gltf_helpers.py
glue_ar/common/tests/helpers.py
glue_ar/common/tests/test_base_dialog.py
glue_ar/common/tests/test_ranged_callback.py
glue_ar/common/tests/test_scatter.py
glue_ar/common/tests/test_scatter_gltf.py
glue_ar/common/tests/test_scatter_stl.py
glue_ar/common/tests/test_scatter_usd.py
glue_ar/common/tests/test_shapes.py
glue_ar/jupyter/__init__.py
glue_ar/jupyter/export_dialog.py
glue_ar/jupyter/export_dialog.vue
glue_ar/jupyter/export_tool.py
glue_ar/jupyter/number_field.py
glue_ar/jupyter/widgets.py
glue_ar/jupyter/tests/__init__.py
glue_ar/jupyter/tests/test_dialog.py
glue_ar/jupyter/tests/test_widgets.py
glue_ar/qt/__init__.py
glue_ar/qt/export_dialog.py
glue_ar/qt/export_dialog.ui
glue_ar/qt/export_tool.py
glue_ar/qt/exporting_dialog.py
glue_ar/qt/qr_dialog.py
glue_ar/qt/qr_dialog.ui
glue_ar/qt/qr_tool.py
glue_ar/qt/server.py
glue_ar/qt/widgets.py
glue_ar/qt/tests/__init__.py
glue_ar/qt/tests/test_dialog.py
glue_ar/qt/tests/test_tool_scatter.py
glue_ar/qt/tests/test_tool_volume.py
glue_ar/qt/tests/test_widgets.py
glue_ar/qt/tests/utils.py
glue_ar/resources/info.png
glue_ar-0.6.0.dist-info/licenses/LICENSE
glue_ar-0.6.0.dist-info/METADATA
glue_ar-0.6.0.dist-info/WHEEL
glue_ar-0.6.0.dist-info/entry_points.txt
glue_ar-0.6.0.dist-info/top_level.txt
glue_ar-0.6.0.dist-info/RECORD
