Metadata-Version: 2.4
Name: glue-ar
Version: 0.6.0
Summary: Export glue views to augmented reality
Author-email: Jonathan Carifio <jonathan.carifio@cfa.harvard.edu>
Project-URL: Homepage, https://glueviz.org/glue-ar
Classifier: Intended Audience :: Science/Research
Classifier: Operating System :: OS Independent
Classifier: Programming Language :: Python
Classifier: Programming Language :: Python :: 3
Classifier: Programming Language :: Python :: 3.10
Classifier: Programming Language :: Python :: 3.11
Classifier: Programming Language :: Python :: 3.12
Classifier: Programming Language :: Python :: 3.13
Classifier: Programming Language :: Python :: 3.14
Classifier: Topic :: Scientific/Engineering :: Visualization
Requires-Python: >=3.10
License-File: LICENSE
Requires-Dist: gltflib
Requires-Dist: glue-core
Requires-Dist: glue-vispy-viewers
Requires-Dist: numpy-stl
Requires-Dist: pillow
Requires-Dist: PyMCubes
Requires-Dist: usd-core
Provides-Extra: test
Requires-Dist: flake8; extra == "test"
Requires-Dist: pytest; extra == "test"
Requires-Dist: pytest-cov; extra == "test"
Provides-Extra: qt
Requires-Dist: glue-qt; extra == "qt"
Requires-Dist: PyQt5; extra == "qt"
Provides-Extra: jupyter
Requires-Dist: glue-jupyter; extra == "jupyter"
Requires-Dist: ipyfilechooser; extra == "jupyter"
Requires-Dist: ipyvuetify; extra == "jupyter"
Requires-Dist: glue-vispy-viewers[jupyter]; extra == "jupyter"
Requires-Dist: ipython-genutils; extra == "jupyter"
Provides-Extra: qr
Requires-Dist: ngrok; extra == "qr"
Requires-Dist: segno; extra == "qr"
Provides-Extra: compression
Requires-Dist: DracoPy; extra == "compression"
Provides-Extra: all
Requires-Dist: glue-ar[test]; extra == "all"
Requires-Dist: glue-ar[qt]; extra == "all"
Requires-Dist: glue-ar[jupyter]; extra == "all"
Requires-Dist: glue-ar[qr]; extra == "all"
Requires-Dist: glue-ar[compression]; extra == "all"
Dynamic: license-file
